 {
   "index": {
     "tiles": [{
       "title": "Justifiable Homicide",
       "subtitle": "A Political Thriller",
       "image": "/images/pic01.jpg",
       "link": "/site/en/content/books/justifiable-homicide"
     }, {
       "title": "Annie and The Senator",
       "subtitle": "A Story of Vigilate Justice",
       "image": "/images/pic02.jpg",
       "link": "/site/en/content/books/annie-and-the-senator"
     }, {
       "title": "The TSA vs The People",
       "subtitle": "A Short Story of Vengeance",
       "image": "/images/pic03.jpg",
       "link": "/site/en/content/books/tsa-vs-the-people"
     }, {
       "title": "The Iraqi Girl",
       "subtitle": "Trilogy Book 1",
       "image": "/images/pic04.jpg",
       "link": "/site/en/content/books/the-iraqi-girl"
     }, {
       "title": "Just Following Orders",
       "subtitle": "Iraqi Girl Trilogy Book 2",
       "image": "/images/pic05.jpg",
       "link": "/site/en/content/books/just-following-orders"
     }, {
       "title": "About Me",
       "subtitle": "See My Biography",
       "image": "/images/pic06.jpg",
       "link": "/site/en/content/books/"
     }]
   }
 }